setup.py
src/greatape/__init__.py
src/greatape.egg-info/PKG-INFO
src/greatape.egg-info/SOURCES.txt
src/greatape.egg-info/dependency_links.txt
src/greatape.egg-info/requires.txt
src/greatape.egg-info/top_level.txt