Metadata-Version: 1.0
Name: greatape
Version: 0.3.0
Summary: A MailChimp API client.
Home-page: http://github.com/threadsafelabs/greatape
Author: Jonathan Lukens
Author-email: UNKNOWN
License: BSD
Platform: UNKNOWN
